setup.py
PivotalTrackerScraper/__init__.py
PivotalTrackerScraper/csvhelper.py
PivotalTrackerScraper/trackerhelper.py
PivotalTrackerScraper/utils.py
bin/track-and-parse-stories
jenkins_trackerscraper.egg-info/PKG-INFO
jenkins_trackerscraper.egg-info/SOURCES.txt
jenkins_trackerscraper.egg-info/dependency_links.txt
jenkins_trackerscraper.egg-info/not-zip-safe
jenkins_trackerscraper.egg-info/requires.txt
jenkins_trackerscraper.egg-info/top_level.txt