Metadata-Version: 1.0
Name: jenkins-trackerscraper
Version: 1.0.0
Summary: Pivotal Tracker Scraper for Jenkins
Home-page: https://github.com/KMK-ONLINE/PivotalTrackerScraper
Author: hxu
Author-email: iosbbmautomationandi@gmail.com
License: MIT
Platform: UNKNOWN
